{"hives": [
    {
        "notes": "First hive to exist.",
        "color": "amber",
        "secondaryPollenSource": "Lavender",
        "name": "Hive1",
        "location": "Alberta",
        "primaryPollenSource": "Wild flower"
    },
    {
        "notes": "Need pest control ASAP.",
        "color": "other",
        "secondaryPollenSource": "Unspecified",
        "name": "Lola's Hive",
        "location": "BC",
        "primaryPollenSource": "Lavender"
    },
    {
        "notes": "Unspecified",
        "color": "other",
        "secondaryPollenSource": "Unspecified",
        "name": "Peanut",
        "location": "Alberta",
        "primaryPollenSource": "Unspecified"
    }
]}